keybind_vault/__about__.py
keybind_vault/__init__.py
keybind_vault/main.py
keybind_vault/db/__init__.py
keybind_vault/db/sqlite_db.py
keybind_vault/modals/__init__.py
keybind_vault/modals/add_modal.py
keybind_vault/modals/delete_modal.py
keybind_vault/modals/edit_modal.py
keybind_vault/modals/search_modal.py
keybind_vault/modals/vault_types.py
keybind_vault/modals/styles/add.tcss
keybind_vault/modals/styles/delete.tcss
keybind_vault/modals/styles/edit.tcss
keybind_vault/modals/styles/search.tcss
keybind_vault/styles/styles.tcss
keybind_vault-1.0.4.dist-info/METADATA
keybind_vault-1.0.4.dist-info/WHEEL
keybind_vault-1.0.4.dist-info/entry_points.txt
keybind_vault-1.0.4.dist-info/licenses/LICENSE
keybind_vault-1.0.4.dist-info/RECORD
