Metadata-Version: 2.4
Name: keybind-vault
Version: 1.0.4
Summary: Text User Interface (TUI) that allows users to manage keybindings
Project-URL: Issues, https://github.com/Thompson6626/Keybind-Vault/issues
Project-URL: Source, https://github.com/Thompson6626/Keybind-Vault
Author-email: Aaron Muñoz <Thompson6626@gmail.com>
License-Expression: MIT
License-File: LICENSE
Requires-Python: >=3.13
Requires-Dist: sqlite-utils>=3.38
Requires-Dist: textual-dev>=1.7.0
Requires-Dist: textual>=3.4.0
Provides-Extra: dev
Requires-Dist: ruff>=0.11.13; extra == 'dev'
